discotp/__init__.py
discotp/bot.py
discotp/config.py
discotp/data.py
discotp/run.py
discotp-1.0.2.dist-info/LICENSE
discotp-1.0.2.dist-info/METADATA
discotp-1.0.2.dist-info/WHEEL
discotp-1.0.2.dist-info/entry_points.txt
discotp-1.0.2.dist-info/RECORD
