Metadata-Version: 2.1
Name: discotp
Version: 1.0.2
Summary: A Discord bot for generating and managing TOTPs (for shared accounts).
License: GPLv3
Author: blobbybilb
Author-email: notablob@outlook.com
Requires-Python: >=3.11,<4.0
Classifier: License :: Other/Proprietary License
Classifier: Programming Language :: Python :: 3
Classifier: Programming Language :: Python :: 3.11
Classifier: Programming Language :: Python :: 3.12
Requires-Dist: discord-py-interactions (>=5.13.2,<6.0.0)
Requires-Dist: pyotp (>=2.9.0,<3.0.0)
Requires-Dist: sqlitedict (>=2.1.0,<3.0.0)
